pgsql.py
pgsql-2.1.dist-info/METADATA
pgsql-2.1.dist-info/WHEEL
pgsql-2.1.dist-info/top_level.txt
pgsql-2.1.dist-info/RECORD
