Metadata-Version: 2.1
Name: pgsql
Version: 2.1
Summary: PostgreSQL client library for Python 3
Author-email: Antti Heinonen <antti@heinonen.cc>
Classifier: Development Status :: 5 - Production/Stable
Classifier: Intended Audience :: Developers
Classifier: License :: OSI Approved :: MIT License
Classifier: Operating System :: OS Independent
Classifier: Programming Language :: Python :: 3
Classifier: Programming Language :: SQL
Classifier: Topic :: Database :: Front-Ends
Classifier: Topic :: Software Development :: Libraries :: Python Modules
Requires-Python: >=3.11
